pypolyagamma/__init__.py
pypolyagamma/binary_trees.py
pypolyagamma/distributions.py
pypolyagamma/pypolyagamma.cpython-37m-darwin.so
pypolyagamma/utils.py
pypolyagamma-1.2.3.dist-info/LICENSE
pypolyagamma-1.2.3.dist-info/METADATA
pypolyagamma-1.2.3.dist-info/WHEEL
pypolyagamma-1.2.3.dist-info/top_level.txt
pypolyagamma-1.2.3.dist-info/RECORD
