Metadata-Version: 1.1
Name: pypolyagamma
Version: 1.2.3
Summary: Cython wrappers for Polya gamma random number generation based on Jesse Windle's BayesLogit package: https://github.com/jwindle/BayesLogit.
Home-page: http://www.github.com/slinderman/pypolyagamma
Author: Scott Linderman
Author-email: scott.linderman@columbia.edu
License: GNU GPLv3
Keywords: monte-carlo,polya,gamma
Platform: ALL
Classifier: Intended Audience :: Science/Research
Classifier: Programming Language :: Python
Classifier: Programming Language :: C++
